{
  "week": 38,
  "days": [
    "// Montag",
    {
      "tagesteller": "Rindsgeschnetzeltes\nnach \"Stroganoff\", Wurzelgemüse und Kartoffelstock",
      "pasta-hit": "Penne a la Carbonara\n(Rahmsauce mit Speck, Zwiebeln und Petersilie)\noder Tomatensauce",
      "nachtessen": "Conchiglie Bündner Art\n(Tomatensauce mit Trockenfleisch und Baumnüssen)"
    },
    "// Dienstag",
    {
      "tagesteller": "Schweinssaltimbocca\nmit Madeirasauce, Ratatouille und Spätzli-Teigwaren\nDessert",
      "pasta-hit": "Penne con Pesto\n(Basilikum, Spinat, Pinienkerne, Sbrinz und Olivenöl)",
      "nachtessen": "Kalbsgemüsehacksteak\nauf Pilzragout mit Raclettekartoffeln"
    },
    "// Mittwoch",
    {
      "tagesteller": "Poulet Cordon-Bleu\nmit Blumenkohl und Tomaten-Risotto",
      "pasta-hit": "Penne con Salmone\n(Rauchlachs, Zwiebeln, Lauch und Dill an Weissweinsauce)\noder Tomatensauce",
      "nachtessen": "Canneloni alla Nonna\nmit Tomatensauce"
    },
    "// Donnerstag",
    {
      "tagesteller": "Schweinsbraten\nmit Lauchgratin und Süsskartoffelgnocchi",
      "pasta-hit": "Penne Bolognese\n(Rindshackfleisch mit Gemüse und brauner Sauce)",
      "nachtessen": "Bratwurst\nan Zwiebelsauce mit Rösti"
    },
    "// Freitag",
    {
      "tagesteller": "Kap-Seehecht\nmit Morgenrotsauce, Zucchettiwürfel und Gemüsereis\nDessert",
      "pasta-hit": "Penne Cinque P\n(Tomatenrahmsauce mit Pfeffer, Petersilie und Sbrinz)",
      "nachtessen": "Abends geschlossen\nLunchbestellung bis zum Frühstück"
    }
  ]
}
